commonground_api_common-2.10.7.data/scripts/generate_schema
vng_api_common/__init__.py
vng_api_common/admin.py
vng_api_common/apps.py
vng_api_common/checks.py
vng_api_common/choices.py
vng_api_common/client.py
vng_api_common/compat.py
vng_api_common/constants.py
vng_api_common/decorators.py
vng_api_common/descriptors.py
vng_api_common/doc.py
vng_api_common/exception_handling.py
vng_api_common/exceptions.py
vng_api_common/fields.py
vng_api_common/filters.py
vng_api_common/filters_backend.py
vng_api_common/filtersets.py
vng_api_common/generators.py
vng_api_common/geo.py
vng_api_common/middleware.py
vng_api_common/mocks.py
vng_api_common/models.py
vng_api_common/oas.py
vng_api_common/pagination.py
vng_api_common/permissions.py
vng_api_common/polymorphism.py
vng_api_common/routers.py
vng_api_common/schema.py
vng_api_common/scopes.py
vng_api_common/search.py
vng_api_common/serializers.py
vng_api_common/urls.py
vng_api_common/utils.py
vng_api_common/validators.py
vng_api_common/version.py
vng_api_common/views.py
vng_api_common/viewsets.py
vng_api_common/api/__init__.py
vng_api_common/api/permissions.py
vng_api_common/api/serializers.py
vng_api_common/api/urls.py
vng_api_common/api/views.py
vng_api_common/audittrails/__init__.py
vng_api_common/audittrails/admin.py
vng_api_common/audittrails/apps.py
vng_api_common/audittrails/audits.py
vng_api_common/audittrails/models.py
vng_api_common/audittrails/utils.py
vng_api_common/audittrails/viewsets.py
vng_api_common/audittrails/api/__init__.py
vng_api_common/audittrails/api/scopes.py
vng_api_common/audittrails/api/serializers.py
vng_api_common/audittrails/migrations/0001_initial.py
vng_api_common/audittrails/migrations/0002_auto_20190516_0830.py
vng_api_common/audittrails/migrations/0003_auto_20190517_0844.py
vng_api_common/audittrails/migrations/0004_auto_20190520_1238.py
vng_api_common/audittrails/migrations/0005_auto_20190520_1450.py
vng_api_common/audittrails/migrations/0006_audittrail_toelichting.py
commonground_api_common-2.10.7.dist-info/METADATA
commonground_api_common-2.10.7.dist-info/WHEEL
commonground_api_common-2.10.7.dist-info/top_level.txt
commonground_api_common-2.10.7.dist-info/RECORD
