Metadata-Version: 2.4
Name: commonground-api-common
Version: 2.10.7
Summary: Commonground API tooling
Home-page: https://github.com/maykinmedia/commonground-api-common
Author: Maykin Media, VNG-Realisatie
Author-email: support@maykinmedia.nl
License: EUPL 1.2
Keywords: openapi,swagger,django
Classifier: Development Status :: 5 - Production/Stable
Classifier: Framework :: Django
Classifier: Framework :: Django :: 5.2
Classifier: Framework :: Django :: 4.2
Classifier: Intended Audience :: Developers
Classifier: Operating System :: Unix
Classifier: Operating System :: MacOS
Classifier: Operating System :: Microsoft :: Windows
Classifier: Programming Language :: Python :: 3
Classifier: Programming Language :: Python :: 3 :: Only
Classifier: Programming Language :: Python :: 3.10
Classifier: Programming Language :: Python :: 3.11
Classifier: Programming Language :: Python :: 3.12
Classifier: Topic :: Software Development :: Libraries :: Python Modules
Requires-Dist: django>=4.2.0
Requires-Dist: django-filter<=25.1,>=23.1
Requires-Dist: django-solo
Requires-Dist: djangorestframework>=3.15.0
Requires-Dist: djangorestframework_camel_case>=1.2.0
Requires-Dist: django-rest-framework-condition
Requires-Dist: drf-nested-routers>=0.94.1
Requires-Dist: drf-spectacular
Requires-Dist: iso639-lang
Requires-Dist: notifications-api-common>=0.3.1
Requires-Dist: zgw-consumers>=1.0.0
Requires-Dist: oyaml
Requires-Dist: PyJWT>=2.10.1
Requires-Dist: requests
Requires-Dist: ape-pie
Requires-Dist: sentry-sdk
Provides-Extra: markdown-docs
Requires-Dist: django-markup<=1.3; extra == "markdown-docs"
Requires-Dist: markdown; extra == "markdown-docs"
Provides-Extra: djangorestframework-gis
Requires-Dist: djangorestframework-gis>=1.0; extra == "djangorestframework-gis"
Provides-Extra: drf-extra-fields
Requires-Dist: drf-extra-fields>=3.7.0; extra == "drf-extra-fields"
Provides-Extra: tests
Requires-Dist: psycopg2; extra == "tests"
Requires-Dist: pytest; extra == "tests"
Requires-Dist: pytest-django; extra == "tests"
Requires-Dist: pytest-dotenv; extra == "tests"
Requires-Dist: pytest-factoryboy>=2.8.0; extra == "tests"
Requires-Dist: tox; extra == "tests"
Requires-Dist: ruff; extra == "tests"
Requires-Dist: requests-mock; extra == "tests"
Requires-Dist: freezegun; extra == "tests"
Requires-Dist: zgw-consumers-oas; extra == "tests"
Requires-Dist: djangorestframework-gis; extra == "tests"
Requires-Dist: drf-extra-fields; extra == "tests"
Provides-Extra: oas
Requires-Dist: requests-mock; extra == "oas"
Provides-Extra: testutils
Requires-Dist: zgw-consumers-oas; extra == "testutils"
Provides-Extra: setup-configuration
Requires-Dist: django-setup-configuration>=0.7.0; extra == "setup-configuration"
Provides-Extra: coverage
Requires-Dist: pytest-cov; extra == "coverage"
Provides-Extra: docs
Requires-Dist: psycopg2; extra == "docs"
Requires-Dist: sphinx; extra == "docs"
Requires-Dist: sphinx-rtd-theme; extra == "docs"
Provides-Extra: release
Requires-Dist: bump2version; extra == "release"
